<annotation>
  <folder>coco</folder>
  <filename>COCO_val2014_000000399942.jpg</filename>
  <path>coco</path>
  <source>
    <database>coco</database>
  </source>
  <size>
    <width>612</width>
    <height>612</height>
    <depth>3</depth>
  </size>
  <segmented>0</segmented>
  <object>
    <name>motorcycle</name>
    <pose>Unspecified</pose>
    <truncated>0</truncated>
    <difficult>0</difficult>
    <bndbox>
      <xmin>406.45</xmin>
      <ymin>409.19</ymin>
      <xmax>431.49</xmax>
      <ymax>450.45</ymax>
    </bndbox>
  </object>
</annotation>
