<annotation>
	<folder>images</folder>
	<filename>898KKSgb5444.jpg</filename>
	<path>./images/00003587.jpg</path>
	<source>
		<database>Europeana Collection</database>
	</source>
	<size>
		<width>469</width>
		<height>600</height>
		<depth>3</depth>
	</size>
	<segmented>0</segmented>
	<object>
		<name>crucifixion</name>
		<pose>Unspecified</pose>
		<truncated>0</truncated>
		<difficult>0</difficult>
		<bndbox>
			<xmin>157</xmin>
			<ymin>12</ymin>
			<xmax>308</xmax>
			<ymax>354</ymax>
		</bndbox>
	</object>
	<object>
		<name>scroll</name>
		<pose>Unspecified</pose>
		<truncated>0</truncated>
		<difficult>0</difficult>
		<bndbox>
			<xmin>210</xmin>
			<ymin>9</ymin>
			<xmax>247</xmax>
			<ymax>65</ymax>
		</bndbox>
	</object>
	<object>
		<name>angel</name>
		<pose>Unspecified</pose>
		<truncated>0</truncated>
		<difficult>0</difficult>
		<bndbox>
			<xmin>308</xmin>
			<ymin>77</ymin>
			<xmax>411</xmax>
			<ymax>227</ymax>
		</bndbox>
	</object>
	<object>
		<name>angel</name>
		<pose>Unspecified</pose>
		<truncated>0</truncated>
		<difficult>0</difficult>
		<bndbox>
			<xmin>328</xmin>
			<ymin>27</ymin>
			<xmax>461</xmax>
			<ymax>138</ymax>
		</bndbox>
	</object>
	<object>
		<name>angel</name>
		<pose>Unspecified</pose>
		<truncated>0</truncated>
		<difficult>0</difficult>
		<bndbox>
			<xmin>15</xmin>
			<ymin>45</ymin>
			<xmax>108</xmax>
			<ymax>170</ymax>
		</bndbox>
	</object>
	<object>
		<name>angel</name>
		<pose>Unspecified</pose>
		<truncated>0</truncated>
		<difficult>0</difficult>
		<bndbox>
			<xmin>54</xmin>
			<ymin>41</ymin>
			<xmax>154</xmax>
			<ymax>199</ymax>
		</bndbox>
	</object>
	<object>
		<name>person</name>
		<pose>Unspecified</pose>
		<truncated>0</truncated>
		<difficult>0</difficult>
		<bndbox>
			<xmin>19</xmin>
			<ymin>245</ymin>
			<xmax>153</xmax>
			<ymax>497</ymax>
		</bndbox>
	</object>
	<object>
		<name>prayer</name>
		<pose>Unspecified</pose>
		<truncated>0</truncated>
		<difficult>0</difficult>
		<bndbox>
			<xmin>155</xmin>
			<ymin>336</ymin>
			<xmax>312</xmax>
			<ymax>548</ymax>
		</bndbox>
	</object>
	<object>
		<name>person</name>
		<pose>Unspecified</pose>
		<truncated>0</truncated>
		<difficult>0</difficult>
		<bndbox>
			<xmin>319</xmin>
			<ymin>235</ymin>
			<xmax>448</xmax>
			<ymax>506</ymax>
		</bndbox>
	</object>
	<object>
		<name>chalice</name>
		<pose>Unspecified</pose>
		<truncated>0</truncated>
		<difficult>0</difficult>
		<bndbox>
			<xmin>156</xmin>
			<ymin>471</ymin>
			<xmax>184</xmax>
			<ymax>530</ymax>
		</bndbox>
	</object>
	<object>
		<name>skull</name>
		<pose>Unspecified</pose>
		<truncated>0</truncated>
		<difficult>0</difficult>
		<bndbox>
			<xmin>177</xmin>
			<ymin>475</ymin>
			<xmax>204</xmax>
			<ymax>502</ymax>
		</bndbox>
	</object>
</annotation>