<annotation>
	<folder>crowns</folder>
	<filename>folger_ill_fac066879.jpg</filename>
	<path>./images/00001988.jpg</path>
	<source>
		<database>Unknown</database>
	</source>
	<size>
		<width>379</width>
		<height>500</height>
		<depth>3</depth>
	</size>
	<segmented>0</segmented>
	<object>
		<name>crown</name>
		<pose>Unspecified</pose>
		<truncated>0</truncated>
		<difficult>0</difficult>
		<bndbox>
			<xmin>198</xmin>
			<ymin>121</ymin>
			<xmax>218</xmax>
			<ymax>132</ymax>
		</bndbox>
	</object>
</annotation>