<annotation>
	<folder>images</folder>
	<filename>angel114.jpg</filename>
	<path>./images/00003750.jpg</path>
	<source>
		<database>Europeana Collection</database>
	</source>
	<size>
		<width>2070</width>
		<height>2500</height>
		<depth>3</depth>
	</size>
	<segmented>0</segmented>
	<object>
		<name>nude</name>
		<pose>Unspecified</pose>
		<truncated>0</truncated>
		<difficult>0</difficult>
		<bndbox>
			<xmin>857</xmin>
			<ymin>877</ymin>
			<xmax>1667</xmax>
			<ymax>2230</ymax>
		</bndbox>
	</object>
	<object>
		<name>nude</name>
		<pose>Unspecified</pose>
		<truncated>0</truncated>
		<difficult>0</difficult>
		<bndbox>
			<xmin>291</xmin>
			<ymin>1224</ymin>
			<xmax>1022</xmax>
			<ymax>2209</ymax>
		</bndbox>
	</object>
	<object>
		<name>nude</name>
		<pose>Unspecified</pose>
		<truncated>0</truncated>
		<difficult>0</difficult>
		<bndbox>
			<xmin>365</xmin>
			<ymin>538</ymin>
			<xmax>1183</xmax>
			<ymax>1253</ymax>
		</bndbox>
	</object>
	<object>
		<name>tree</name>
		<pose>Unspecified</pose>
		<truncated>0</truncated>
		<difficult>0</difficult>
		<bndbox>
			<xmin>1193</xmin>
			<ymin>145</ymin>
			<xmax>1906</xmax>
			<ymax>1188</ymax>
		</bndbox>
	</object>
	<object>
		<name>tree</name>
		<pose>Unspecified</pose>
		<truncated>0</truncated>
		<difficult>0</difficult>
		<bndbox>
			<xmin>151</xmin>
			<ymin>166</ymin>
			<xmax>417</xmax>
			<ymax>630</ymax>
		</bndbox>
	</object>
</annotation>