<annotation>
	<folder>bananas_apples_oranges</folder>
	<filename>apple_9.jpg</filename>
	<path>./images/00002648.jpg</path>
	<source>
		<database>WikiArt</database>
	</source>
	<size>
		<width>1200</width>
		<height>934</height>
		<depth>3</depth>
	</size>
	<segmented>0</segmented>
	<object>
		<name>apple</name>
		<pose>Unspecified</pose>
		<truncated>0</truncated>
		<difficult>0</difficult>
		<bndbox>
			<xmin>606</xmin>
			<ymin>256</ymin>
			<xmax>780</xmax>
			<ymax>421</ymax>
		</bndbox>
	</object>
	<object>
		<name>apple</name>
		<pose>Unspecified</pose>
		<truncated>0</truncated>
		<difficult>0</difficult>
		<bndbox>
			<xmin>466</xmin>
			<ymin>352</ymin>
			<xmax>610</xmax>
			<ymax>494</ymax>
		</bndbox>
	</object>
	<object>
		<name>apple</name>
		<pose>Unspecified</pose>
		<truncated>0</truncated>
		<difficult>0</difficult>
		<bndbox>
			<xmin>589</xmin>
			<ymin>356</ymin>
			<xmax>752</xmax>
			<ymax>516</ymax>
		</bndbox>
	</object>
	<object>
		<name>apple</name>
		<pose>Unspecified</pose>
		<truncated>0</truncated>
		<difficult>0</difficult>
		<bndbox>
			<xmin>757</xmin>
			<ymin>315</ymin>
			<xmax>928</xmax>
			<ymax>486</ymax>
		</bndbox>
	</object>
	<object>
		<name>apple</name>
		<pose>Unspecified</pose>
		<truncated>0</truncated>
		<difficult>0</difficult>
		<bndbox>
			<xmin>986</xmin>
			<ymin>591</ymin>
			<xmax>1159</xmax>
			<ymax>755</ymax>
		</bndbox>
	</object>
</annotation>