<annotation>
	<folder>boats</folder>
	<filename>boats-on-the-beach-at-etretat.jpg</filename>
	<path>/home/bscuser/BSC/datasets/WikiArt/boats/boats-on-the-beach-at-etretat.jpg</path>
	<source>
		<database>Unknown</database>
	</source>
	<size>
		<width>1280</width>
		<height>1023</height>
		<depth>3</depth>
	</size>
	<segmented>0</segmented>
	<object>
		<name>boat</name>
		<pose>Unspecified</pose>
		<truncated>0</truncated>
		<difficult>0</difficult>
		<bndbox>
			<xmin>334</xmin>
			<ymin>868</ymin>
			<xmax>641</xmax>
			<ymax>1003</ymax>
		</bndbox>
	</object>
	<object>
		<name>boat</name>
		<pose>Unspecified</pose>
		<truncated>0</truncated>
		<difficult>0</difficult>
		<bndbox>
			<xmin>812</xmin>
			<ymin>653</ymin>
			<xmax>1061</xmax>
			<ymax>737</ymax>
		</bndbox>
	</object>
</annotation>
