<annotation>
	<folder>cats</folder>
	<filename>cosmic-energy.jpg</filename>
	<path>./images/00001480.jpg</path>
	<source>
		<database>WikiArt</database>
	</source>
	<size>
		<width>920</width>
		<height>941</height>
		<depth>3</depth>
	</size>
	<segmented>0</segmented>
	<object>
		<name>cat</name>
		<pose>Unspecified</pose>
		<truncated>0</truncated>
		<difficult>0</difficult>
		<bndbox>
			<xmin>187</xmin>
			<ymin>497</ymin>
			<xmax>390</xmax>
			<ymax>769</ymax>
		</bndbox>
	</object>
</annotation>