<annotation>
	<folder>images</folder>
	<filename>123adam-and-eve.jpg</filename>
	<path>./images/00002935.jpg</path>
	<source>
		<database>WikiArt</database>
	</source>
	<size>
		<width>701</width>
		<height>1074</height>
		<depth>3</depth>
	</size>
	<segmented>0</segmented>
	<object>
		<name>nude</name>
		<pose>Unspecified</pose>
		<truncated>0</truncated>
		<difficult>0</difficult>
		<bndbox>
			<xmin>223</xmin>
			<ymin>45</ymin>
			<xmax>680</xmax>
			<ymax>1071</ymax>
		</bndbox>
	</object>
	<object>
		<name>nude</name>
		<pose>Unspecified</pose>
		<truncated>0</truncated>
		<difficult>0</difficult>
		<bndbox>
			<xmin>40</xmin>
			<ymin>59</ymin>
			<xmax>366</xmax>
			<ymax>1049</ymax>
		</bndbox>
	</object>
	<object>
		<name>apple</name>
		<pose>Unspecified</pose>
		<truncated>0</truncated>
		<difficult>0</difficult>
		<bndbox>
			<xmin>219</xmin>
			<ymin>178</ymin>
			<xmax>278</xmax>
			<ymax>240</ymax>
		</bndbox>
	</object>
	<object>
		<name>apple</name>
		<pose>Unspecified</pose>
		<truncated>0</truncated>
		<difficult>0</difficult>
		<bndbox>
			<xmin>651</xmin>
			<ymin>332</ymin>
			<xmax>698</xmax>
			<ymax>387</ymax>
		</bndbox>
	</object>
	<object>
		<name>apple</name>
		<pose>Unspecified</pose>
		<truncated>1</truncated>
		<difficult>0</difficult>
		<bndbox>
			<xmin>62</xmin>
			<ymin>1</ymin>
			<xmax>114</xmax>
			<ymax>49</ymax>
		</bndbox>
	</object>
	<object>
		<name>apple</name>
		<pose>Unspecified</pose>
		<truncated>0</truncated>
		<difficult>0</difficult>
		<bndbox>
			<xmin>15</xmin>
			<ymin>49</ymin>
			<xmax>73</xmax>
			<ymax>105</ymax>
		</bndbox>
	</object>
	<object>
		<name>tree</name>
		<pose>Unspecified</pose>
		<truncated>1</truncated>
		<difficult>0</difficult>
		<bndbox>
			<xmin>161</xmin>
			<ymin>6</ymin>
			<xmax>701</xmax>
			<ymax>1027</ymax>
		</bndbox>
	</object>
</annotation>