<annotation>
	<folder>zebra</folder>
	<filename>403h_yEpoHqayz3swikaw3bcCrnAdoouHrj7AlsdVPKyGmBcpGcGZoFOzJJVu3yOm74v8IScZINOWjkHIjUOiO9XqvaMdU.jpg</filename>
	<path>./images/00001843.jpg</path>
	<source>
		<database>Europeana Collection</database>
	</source>
	<size>
		<width>2500</width>
		<height>1862</height>
		<depth>3</depth>
	</size>
	<segmented>0</segmented>
	<object>
		<name>zebra</name>
		<pose>Unspecified</pose>
		<truncated>0</truncated>
		<difficult>0</difficult>
		<bndbox>
			<xmin>604</xmin>
			<ymin>935</ymin>
			<xmax>1929</xmax>
			<ymax>1796</ymax>
		</bndbox>
	</object>
</annotation>