<annotation>
	<folder>lion</folder>
	<filename>1796E092249.jpg</filename>
	<path>./images/00004042.jpg</path>
	<source>
		<database>Europeana Collection</database>
	</source>
	<size>
		<width>1500</width>
		<height>1002</height>
		<depth>3</depth>
	</size>
	<segmented>0</segmented>
	<object>
		<name>lion</name>
		<pose>Unspecified</pose>
		<truncated>0</truncated>
		<difficult>0</difficult>
		<bndbox>
			<xmin>722</xmin>
			<ymin>359</ymin>
			<xmax>1137</xmax>
			<ymax>870</ymax>
		</bndbox>
	</object>
	<object>
		<name>lion</name>
		<pose>Unspecified</pose>
		<truncated>0</truncated>
		<difficult>0</difficult>
		<bndbox>
			<xmin>1069</xmin>
			<ymin>417</ymin>
			<xmax>1386</xmax>
			<ymax>865</ymax>
		</bndbox>
	</object>
	<object>
		<name>lion</name>
		<pose>Unspecified</pose>
		<truncated>0</truncated>
		<difficult>0</difficult>
		<bndbox>
			<xmin>962</xmin>
			<ymin>363</ymin>
			<xmax>1230</xmax>
			<ymax>648</ymax>
		</bndbox>
	</object>
	<object>
		<name>lion</name>
		<pose>Unspecified</pose>
		<truncated>0</truncated>
		<difficult>0</difficult>
		<bndbox>
			<xmin>657</xmin>
			<ymin>623</ymin>
			<xmax>1192</xmax>
			<ymax>836</ymax>
		</bndbox>
	</object>
	<object>
		<name>serpent</name>
		<pose>Unspecified</pose>
		<truncated>0</truncated>
		<difficult>0</difficult>
		<bndbox>
			<xmin>485</xmin>
			<ymin>783</ymin>
			<xmax>986</xmax>
			<ymax>884</ymax>
		</bndbox>
	</object>
	<object>
		<name>dragon</name>
		<pose>Unspecified</pose>
		<truncated>0</truncated>
		<difficult>0</difficult>
		<bndbox>
			<xmin>1279</xmin>
			<ymin>424</ymin>
			<xmax>1388</xmax>
			<ymax>578</ymax>
		</bndbox>
	</object>
	<object>
		<name>tree</name>
		<pose>Unspecified</pose>
		<truncated>0</truncated>
		<difficult>0</difficult>
		<bndbox>
			<xmin>1108</xmin>
			<ymin>268</ymin>
			<xmax>1386</xmax>
			<ymax>446</ymax>
		</bndbox>
	</object>
	<object>
		<name>tree</name>
		<pose>Unspecified</pose>
		<truncated>0</truncated>
		<difficult>0</difficult>
		<bndbox>
			<xmin>1171</xmin>
			<ymin>91</ymin>
			<xmax>1357</xmax>
			<ymax>247</ymax>
		</bndbox>
	</object>
	<object>
		<name>tree</name>
		<pose>Unspecified</pose>
		<truncated>0</truncated>
		<difficult>0</difficult>
		<bndbox>
			<xmin>832</xmin>
			<ymin>109</ymin>
			<xmax>1045</xmax>
			<ymax>262</ymax>
		</bndbox>
	</object>
	<object>
		<name>banner</name>
		<pose>Unspecified</pose>
		<truncated>0</truncated>
		<difficult>0</difficult>
		<bndbox>
			<xmin>317</xmin>
			<ymin>104</ymin>
			<xmax>411</xmax>
			<ymax>242</ymax>
		</bndbox>
	</object>
	<object>
		<name>lance</name>
		<pose>Unspecified</pose>
		<truncated>0</truncated>
		<difficult>0</difficult>
		<bndbox>
			<xmin>471</xmin>
			<ymin>109</ymin>
			<xmax>753</xmax>
			<ymax>229</ymax>
		</bndbox>
	</object>
	<object>
		<name>lance</name>
		<pose>Unspecified</pose>
		<truncated>0</truncated>
		<difficult>0</difficult>
		<bndbox>
			<xmin>541</xmin>
			<ymin>412</ymin>
			<xmax>831</xmax>
			<ymax>654</ymax>
		</bndbox>
	</object>
	<object>
		<name>lance</name>
		<pose>Unspecified</pose>
		<truncated>0</truncated>
		<difficult>0</difficult>
		<bndbox>
			<xmin>409</xmin>
			<ymin>96</ymin>
			<xmax>516</xmax>
			<ymax>321</ymax>
		</bndbox>
	</object>
	<object>
		<name>lance</name>
		<pose>Unspecified</pose>
		<truncated>0</truncated>
		<difficult>0</difficult>
		<bndbox>
			<xmin>274</xmin>
			<ymin>92</ymin>
			<xmax>327</xmax>
			<ymax>322</ymax>
		</bndbox>
	</object>
	<object>
		<name>lance</name>
		<pose>Unspecified</pose>
		<truncated>0</truncated>
		<difficult>0</difficult>
		<bndbox>
			<xmin>243</xmin>
			<ymin>99</ymin>
			<xmax>283</xmax>
			<ymax>300</ymax>
		</bndbox>
	</object>
	<object>
		<name>lance</name>
		<pose>Unspecified</pose>
		<truncated>0</truncated>
		<difficult>0</difficult>
		<bndbox>
			<xmin>228</xmin>
			<ymin>101</ymin>
			<xmax>248</xmax>
			<ymax>299</ymax>
		</bndbox>
	</object>
	<object>
		<name>lance</name>
		<pose>Unspecified</pose>
		<truncated>0</truncated>
		<difficult>0</difficult>
		<bndbox>
			<xmin>193</xmin>
			<ymin>92</ymin>
			<xmax>225</xmax>
			<ymax>300</ymax>
		</bndbox>
	</object>
	<object>
		<name>lance</name>
		<pose>Unspecified</pose>
		<truncated>0</truncated>
		<difficult>0</difficult>
		<bndbox>
			<xmin>158</xmin>
			<ymin>99</ymin>
			<xmax>194</xmax>
			<ymax>304</ymax>
		</bndbox>
	</object>
	<object>
		<name>lance</name>
		<pose>Unspecified</pose>
		<truncated>0</truncated>
		<difficult>0</difficult>
		<bndbox>
			<xmin>111</xmin>
			<ymin>122</ymin>
			<xmax>139</xmax>
			<ymax>292</ymax>
		</bndbox>
	</object>
	<object>
		<name>banner</name>
		<pose>Unspecified</pose>
		<truncated>0</truncated>
		<difficult>0</difficult>
		<bndbox>
			<xmin>114</xmin>
			<ymin>90</ymin>
			<xmax>232</xmax>
			<ymax>140</ymax>
		</bndbox>
	</object>
	<object>
		<name>sword</name>
		<pose>Unspecified</pose>
		<truncated>0</truncated>
		<difficult>0</difficult>
		<bndbox>
			<xmin>195</xmin>
			<ymin>225</ymin>
			<xmax>457</xmax>
			<ymax>320</ymax>
		</bndbox>
	</object>
	<object>
		<name>sword</name>
		<pose>Unspecified</pose>
		<truncated>0</truncated>
		<difficult>0</difficult>
		<bndbox>
			<xmin>404</xmin>
			<ymin>177</ymin>
			<xmax>523</xmax>
			<ymax>317</ymax>
		</bndbox>
	</object>
	<object>
		<name>sword</name>
		<pose>Unspecified</pose>
		<truncated>0</truncated>
		<difficult>0</difficult>
		<bndbox>
			<xmin>630</xmin>
			<ymin>156</ymin>
			<xmax>923</xmax>
			<ymax>271</ymax>
		</bndbox>
	</object>
	<object>
		<name>sword</name>
		<pose>Unspecified</pose>
		<truncated>0</truncated>
		<difficult>0</difficult>
		<bndbox>
			<xmin>354</xmin>
			<ymin>551</ymin>
			<xmax>489</xmax>
			<ymax>825</ymax>
		</bndbox>
	</object>
	<object>
		<name>crown</name>
		<pose>Unspecified</pose>
		<truncated>0</truncated>
		<difficult>0</difficult>
		<bndbox>
			<xmin>612</xmin>
			<ymin>291</ymin>
			<xmax>705</xmax>
			<ymax>368</ymax>
		</bndbox>
	</object>
	<object>
		<name>knight</name>
		<pose>Unspecified</pose>
		<truncated>0</truncated>
		<difficult>0</difficult>
		<bndbox>
			<xmin>539</xmin>
			<ymin>328</ymin>
			<xmax>758</xmax>
			<ymax>804</ymax>
		</bndbox>
	</object>
	<object>
		<name>knight</name>
		<pose>Unspecified</pose>
		<truncated>0</truncated>
		<difficult>0</difficult>
		<bndbox>
			<xmin>427</xmin>
			<ymin>319</ymin>
			<xmax>655</xmax>
			<ymax>776</ymax>
		</bndbox>
	</object>
	<object>
		<name>knight</name>
		<pose>Unspecified</pose>
		<truncated>0</truncated>
		<difficult>0</difficult>
		<bndbox>
			<xmin>256</xmin>
			<ymin>356</ymin>
			<xmax>487</xmax>
			<ymax>808</ymax>
		</bndbox>
	</object>
	<object>
		<name>knight</name>
		<pose>Unspecified</pose>
		<truncated>0</truncated>
		<difficult>0</difficult>
		<bndbox>
			<xmin>99</xmin>
			<ymin>360</ymin>
			<xmax>348</xmax>
			<ymax>840</ymax>
		</bndbox>
	</object>
	<object>
		<name>knight</name>
		<pose>Unspecified</pose>
		<truncated>0</truncated>
		<difficult>0</difficult>
		<bndbox>
			<xmin>262</xmin>
			<ymin>312</ymin>
			<xmax>376</xmax>
			<ymax>484</ymax>
		</bndbox>
	</object>
	<object>
		<name>knight</name>
		<pose>Unspecified</pose>
		<truncated>0</truncated>
		<difficult>0</difficult>
		<bndbox>
			<xmin>654</xmin>
			<ymin>192</ymin>
			<xmax>777</xmax>
			<ymax>705</ymax>
		</bndbox>
	</object>
	<object>
		<name>knight</name>
		<pose>Unspecified</pose>
		<truncated>0</truncated>
		<difficult>0</difficult>
		<bndbox>
			<xmin>758</xmin>
			<ymin>209</ymin>
			<xmax>925</xmax>
			<ymax>676</ymax>
		</bndbox>
	</object>
	<object>
		<name>knight</name>
		<pose>Unspecified</pose>
		<truncated>0</truncated>
		<difficult>0</difficult>
		<bndbox>
			<xmin>111</xmin>
			<ymin>323</ymin>
			<xmax>199</xmax>
			<ymax>791</ymax>
		</bndbox>
	</object>
</annotation>