<annotation>
	<folder>sheeps</folder>
	<filename>57bathing-of-a-sheeps-1877.jpg</filename>
	<path>./images/00001654.jpg</path>
	<source>
		<database>WikiArt</database>
	</source>
	<size>
		<width>1103</width>
		<height>826</height>
		<depth>3</depth>
	</size>
	<segmented>0</segmented>
	<object>
		<name>shepherd</name>
		<pose>Unspecified</pose>
		<truncated>0</truncated>
		<difficult>0</difficult>
		<bndbox>
			<xmin>244</xmin>
			<ymin>608</ymin>
			<xmax>313</xmax>
			<ymax>729</ymax>
		</bndbox>
	</object>
	<object>
		<name>shepherd</name>
		<pose>Unspecified</pose>
		<truncated>0</truncated>
		<difficult>0</difficult>
		<bndbox>
			<xmin>514</xmin>
			<ymin>615</ymin>
			<xmax>574</xmax>
			<ymax>691</ymax>
		</bndbox>
	</object>
	<object>
		<name>boat</name>
		<pose>Unspecified</pose>
		<truncated>0</truncated>
		<difficult>0</difficult>
		<bndbox>
			<xmin>122</xmin>
			<ymin>381</ymin>
			<xmax>387</xmax>
			<ymax>612</ymax>
		</bndbox>
	</object>
	<object>
		<name>boat</name>
		<pose>Unspecified</pose>
		<truncated>1</truncated>
		<difficult>0</difficult>
		<bndbox>
			<xmin>1</xmin>
			<ymin>400</ymin>
			<xmax>189</xmax>
			<ymax>614</ymax>
		</bndbox>
	</object>
	<object>
		<name>sheep</name>
		<pose>Unspecified</pose>
		<truncated>0</truncated>
		<difficult>0</difficult>
		<bndbox>
			<xmin>437</xmin>
			<ymin>718</ymin>
			<xmax>543</xmax>
			<ymax>780</ymax>
		</bndbox>
	</object>
	<object>
		<name>sheep</name>
		<pose>Unspecified</pose>
		<truncated>0</truncated>
		<difficult>0</difficult>
		<bndbox>
			<xmin>381</xmin>
			<ymin>756</ymin>
			<xmax>487</xmax>
			<ymax>818</ymax>
		</bndbox>
	</object>
	<object>
		<name>sheep</name>
		<pose>Unspecified</pose>
		<truncated>0</truncated>
		<difficult>0</difficult>
		<bndbox>
			<xmin>648</xmin>
			<ymin>728</ymin>
			<xmax>718</xmax>
			<ymax>785</ymax>
		</bndbox>
	</object>
	<object>
		<name>sheep</name>
		<pose>Unspecified</pose>
		<truncated>0</truncated>
		<difficult>0</difficult>
		<bndbox>
			<xmin>596</xmin>
			<ymin>716</ymin>
			<xmax>651</xmax>
			<ymax>767</ymax>
		</bndbox>
	</object>
	<object>
		<name>sheep</name>
		<pose>Unspecified</pose>
		<truncated>0</truncated>
		<difficult>0</difficult>
		<bndbox>
			<xmin>157</xmin>
			<ymin>696</ymin>
			<xmax>217</xmax>
			<ymax>760</ymax>
		</bndbox>
	</object>
	<object>
		<name>sheep</name>
		<pose>Unspecified</pose>
		<truncated>0</truncated>
		<difficult>0</difficult>
		<bndbox>
			<xmin>276</xmin>
			<ymin>677</ymin>
			<xmax>335</xmax>
			<ymax>725</ymax>
		</bndbox>
	</object>
	<object>
		<name>sheep</name>
		<pose>Unspecified</pose>
		<truncated>0</truncated>
		<difficult>0</difficult>
		<bndbox>
			<xmin>554</xmin>
			<ymin>699</ymin>
			<xmax>610</xmax>
			<ymax>755</ymax>
		</bndbox>
	</object>
</annotation>