<annotation>
	<folder>dogs</folder>
	<filename>IIHIM_1552974788.jpg</filename>
	<path>/home/bscuser/BSC/datasets/dogs/IIHIM_1552974788.jpg</path>
	<source>
		<database>Unknown</database>
	</source>
	<size>
		<width>417</width>
		<height>500</height>
		<depth>3</depth>
	</size>
	<segmented>0</segmented>
	<object>
		<name>dog</name>
		<pose>Unspecified</pose>
		<truncated>0</truncated>
		<difficult>0</difficult>
		<bndbox>
			<xmin>133</xmin>
			<ymin>446</ymin>
			<xmax>190</xmax>
			<ymax>476</ymax>
		</bndbox>
	</object>
	<object>
		<name>dog</name>
		<pose>Unspecified</pose>
		<truncated>0</truncated>
		<difficult>0</difficult>
		<bndbox>
			<xmin>48</xmin>
			<ymin>410</ymin>
			<xmax>99</xmax>
			<ymax>455</ymax>
		</bndbox>
	</object>
</annotation>
